{
    "$schema": "http://json-schema.org/draft-07/schema#",
    "title": "Auxiliary Digital Token",
    "LastModifyDateTime": "2023-12-18T14:48:40",
    "description": "Non-native digital token created as an application on an existing blockchain or other distributed ledger technology for its issuance, storage, or transaction record",
    "copyright": "Copyright \u00a9 2021 Digital Token Identifier Foundation Limited 2021. All Rights Reserved.",
    "type": "object",
    "properties": {
        "Header": {
            "type": "object",
            "properties": {
                "DTI": {
                    "title": "Digital Token Identifier",
                    "description": "",
                    "type": "string"
                },
                "DTIType": {
                    "title": "Digital Token Identifier Type",
                    "description": "Category of the digital token identifier",
                    "type": "integer",
                    "const": 0,
                    "enum": [
                        0,
                        1,
                        2,
                        3
                    ],
                    "options": {
                        "enum_titles": [
                            "Auxiliary Digital Token",
                            "Native Digital Token",
                            "Distributed Ledger without a Native Digital Token",
                            "Functionally Fungible Group of Digital Tokens"
                        ]
                    }
                },
                "templateVersion": {
                    "title": "Template Version",
                    "description": "The template version (i.e. JSON schema document) for which this record is valid",
                    "type": "string",
                    "const": "V1.0.0",
                    "enum": [
                        "V1.0.0"
                    ]
                }
            },
            "required": [
                "DTI",
                "DTIType",
                "templateVersion"
            ],
            "additionalProperties": false
        },
        "Informative": {
            "type": "object",
            "properties": {
                "LongName": {
                    "condition": "Conditionally required for non provisional records",
                    "title": "Digital Token Long Name",
                    "description": "Digital token long name is a string containing the full name of the digital token",
                    "type": "string"
                },
                "OrigLangLongName": {
                    "title": "Original Language Digital Token Long Name",
                    "description": "",
                    "type": "string",
                    "default": "Basic Latin (Unicode)"
                },
                "ShortNames": {
                    "type": "array",
                    "uniqueItems": true,
                    "items": {
                        "type": "object",
                        "properties": {
                            "ShortName": {
                                "title": "Digital Token Digital Token Short Name",
                                "description": "Short name or ticker symbol of the digital token",
                                "type": "string"
                            },
                            "OrigLangShortName": {
                                "title": "Original Language Digital Token Short Name",
                                "description": "",
                                "type": "string",
                                "default": "Basic Latin (Unicode)"
                            }
                        },
                        "required": [
                            "ShortName"
                        ],
                        "additionalProperties": false
                    }
                },
                "UnderlyingAssetExternalIdentifiers": {
                    "type": "array",
                    "uniqueItems": true,
                    "items": {
                        "type": "object",
                        "properties": {
                            "UnderlyingAssetExternalIdentifierType": {
                                "title": "Underlying Asset External Identifier Type",
                                "description": "Underlying asset external identifier type for the digital token",
                                "type": "string",
                                "elaboration": "Underlying Asset Types",
                                "enum": [
                                    "ISIN",
                                    "Cusip",
                                    "SEDOL",
                                    "RIC",
                                    "CCY",
                                    "Country code",
                                    "FIGI",
                                    "LEI"
                                ],
                                "enum_elaboration": {
                                    "ISIN": "ISO 6166",
                                    "Cusip": "Cusip",
                                    "SEDOL": "Stock Exchange Daily Official List assigned by the London Stock Exchange",
                                    "RIC": "RIC",
                                    "CCY": "ISO 4217",
                                    "Country code": "ISO 3166 ALPHA 3",
                                    "FIGI": "An Object Management Group (OMG) standard; Formerly known as \"Bloomberg Open Symbology BBGID\"",
                                    "LEI": "ISO 17442"
                                },
                                "options": {
                                    "enum_titles": [
                                        "International Securities Identification Number",
                                        "",
                                        "Stock Exchange Daily Official List",
                                        "Reuters Instrument Code",
                                        "Currency Code",
                                        "",
                                        "Financial Instrument Global Identifier",
                                        "Legal Entity Identifier"
                                    ]
                                }
                            },
                            "UnderlyingAssetExternalIdentifierValue": {
                                "title": "Underlying Asset External Identifier Value",
                                "description": "Underlying asset external identifier value for the digital token",
                                "type": "string"
                            }
                        },
                        "required": [
                            "UnderlyingAssetExternalIdentifierType",
                            "UnderlyingAssetExternalIdentifierValue"
                        ],
                        "additionalProperties": false
                    }
                },
                "DTIExternalIdentifiers": {
                    "type": "array",
                    "uniqueItems": true,
                    "items": {
                        "type": "object",
                        "properties": {
                            "DTIExternalIdentifierType": {
                                "title": "Digital Token External Identifier Type",
                                "description": "External identifier type for the digital token",
                                "type": "string",
                                "elaboration": "External Digital Token Identifier Types",
                                "enum": [
                                    "ITIN"
                                ],
                                "options": {
                                    "enum_titles": [
                                        "International Token Identification Number"
                                    ]
                                }
                            },
                            "ExternalIdentifierValue": {
                                "title": "Digital Token External Identifier Value",
                                "description": "External identifier for the digital token",
                                "type": "string"
                            }
                        },
                        "required": [
                            "DTIExternalIdentifierType",
                            "ExternalIdentifierValue"
                        ],
                        "additionalProperties": false
                    }
                },
                "UnitMultiplier": {
                    "condition": "Conditionally required for non provisional records",
                    "title": "Digital Token Unit Multiplier",
                    "description": "Multiplier used to map from the unit of value stored on the distributed ledger to the unit of value associated with the digital token long name",
                    "type": "integer"
                }
            },
            "additionalProperties": false
        },
        "Normative": {
            "type": "object",
            "properties": {
                "AuxiliaryMechanism": {
                    "condition": "Conditionally required for non provisional records",
                    "title": "Auxiliary Digital Token Mechanism",
                    "description": "",
                    "type": "string",
                    "elaboration": "Auxiliary Digital Token Mechanism",
                    "enum": [
                        "ATS",
                        "ASA",
                        "BEP-2",
                        "BEP-20",
                        "Cardano Smart Contract",
                        "CRC20",
                        "CW20",
                        "ERC-20",
                        "EOSIO.TOKEN",
                        "FA2",
                        "FT",
                        "Fungible CashToken",
                        "GSDAP",
                        "HRC20",
                        "HRC-20",
                        "HTS",
                        "IBC Coin",
                        "Jetton",
                        "KIP-7",
                        "KIP-20",
                        "LiquidAsset",
                        "Native Attribute",
                        "Native Coin",
                        "NEP-5",
                        "NEP-141",
                        "OMNI",
                        "SEP-1",
                        "SEP20",
                        "SORA Token",
                        "SPL-Token",
                        "StatemineAsset",
                        "StatemintAsset",
                        "TRC-10",
                        "TRC-20",
                        "SDX",
                        "SLP Token",
                        "WSC"
                    ],
                    "enum_elaboration": {
                        "ATS": "Aptos identifies a token by its TokenId that includes TokenDataId and property_version.",
                        "ASA": "The Algorand protocol supports the creation of on-chain assets that benefit from the same security, compatibility, speed and ease of use as the Algo. The official name for assets on Algorand is Algorand Standard Assets (ASA).",
                        "BEP-2": "BEP-2 is a technical standard for the issuance and implementation of tokens on the Binance Chain",
                        "BEP-20": "BEP-20 is a technical standard for the issuance and implementation of tokens on the Binance Chain",
                        "Cardano Smart Contract": "Cardano smart contracts are digital agreements defined in code that automate and enforce the terms of a contract without the need for intermediaries, enabling secure and transparent transactions on Cardano blockchain.",
                        "CRC20": "Cronos Token Standard that implements an API for tokens within Smart Contracts",
                        "CW20": "CW20 is a specification for fungible tokens based on CosmWasm",
                        "ERC-20": "Ethereum Token Standard that implements an API for tokens within Smart Contracts.",
                        "EOSIO.TOKEN": "Smart Contract standard implementation on EOSIO blockchain",
                        "FA2": "FA2 is a token standard on Tezos",
                        "FT": "The FT is a specification for creating and managing fungible tokens on Flow blockchain, which are tokens with equal value and interchangeable.",
                        "Fungible CashToken": "A token is an asset \u2013 distinct from the Bitcoin Cash currency \u2013 that can be created and transferred on the Bitcoin Cash network.",
                        "GSDAP": "Digital token mechanism on GS DAP ledger",
                        "HRC20": "HRC-20 are fungible tokens minted on the Harmony network, much like ERC-20 tokens are on Ethereum.",
                        "HRC-20": "Heco blockchain protocol, fully compatible with ERC20 standard.",
                        "HTS": "A token service on the Hedera ledger. This service defines a common implementation for Fungible and Non Fungible tokens.",
                        "IBC Coin": "The Inter-Blockchain Communication Protocol (IBC) is a protocol to handle authentication and transport of data between two blockchains on Cosmos ecosystem.",
                        "Jetton": "A Jetton is a smart contract implementing a fungible token",
                        "KIP-7": "A fungible token standard for Klaytn.",
                        "KIP-20": "Smart Contract Tokens on OKExChain",
                        "LiquidAsset": "Liquid assets are tokens issued on the Liquid Network",
                        "Native Attribute": "A DTI reference to the definition of the variable defining the token. Native Data Structures are used to distinguish co-native tokens",
                        "Native Coin": "A native coin used in the Cosmos ecosystem.",
                        "NEP-5": "The NEP-5 standard is a token standard which represents a tokenized smart contract.",
                        "NEP-141": "A standard interface for fungible tokens that allows for a normal transfer as well as a transfer and method call in a single transaction on NEAR Protocol.",
                        "OMNI": "Omni is a platform for creating and trading custom digital assets and currencies.",
                        "SEP-1": "Stellar Ecosystem Proposals are open protocols for building on top of Stellar, and the very first SEP, aptly named SEP-1, specifies everything you could ever want to include in a stellar.toml file",
                        "SEP20": "This SEP proposes an interface standard to create token contracts on smartBCH",
                        "SORA Token": "SORA blockchain protocol.",
                        "SPL-Token": "A Token program on the Solana blockchain. This program defines a common implementation for Fungible and Non Fungible tokens",
                        "StatemineAsset": "Asset issued on Statemine, a parachain of Kusama",
                        "StatemintAsset": "Asset issued on Statemint, a parachain of Polkadot",
                        "TRC-10": "TRC-10 tokens are issued by system contract. TRC-10 is a technical token standard supported by the TRON blockchain natively without the TRON Virtual Machine (TVM)",
                        "TRC-20": "TRC-20 is a technical standard used for smart contracts on the TRON blockchain for implementing tokens with the TRON Virtual Machine (TVM).",
                        "SDX": "Digital token mechanism on SDX R3 Corda Ledger",
                        "SLP Token": "Simple Ledger Protocol is a token system for the Bitcoin Cash network. It allows users to create, issue, and transfer digital tokens that enjoy the same security model and network of Bitcoin Cash.",
                        "WSC": "Smart contracts on the Waves blockchain are accounts and assets with assigned scripts written in Ride."
                    },
                    "options": {
                        "enum_titles": [
                            "Aptos token standard",
                            "Algorand Standard Assets",
                            "Binance Chain Evolution Proposal 2",
                            "Binance Chain Evolution Proposal 20",
                            "Cardano Smart Contract",
                            "Cronos Request for Comments 20",
                            "CosmWasm 20",
                            "Ethereum Request for Comments 20",
                            "EOSIO.TOKEN",
                            "FA2",
                            "Fungible Token Standard",
                            "Fungible CashToken",
                            "GSDAP",
                            "Harmony Request for Comments",
                            "Heco Request for Comments",
                            "Hedera Token Service",
                            "Inter-Blockchain Communication Protocol Coin",
                            "Jetton",
                            "Klaytn Fungible Token Standard",
                            "KIP-20",
                            "LiquidAsset",
                            "Native Attribute",
                            "Native Coin",
                            "NEO Enhancement Protocol",
                            "Near Protocol Ecosystem Tokens",
                            "Bitcoin Omni Layer",
                            "Stellar Ecosystem Proposal",
                            "SEP20",
                            "SORA Token",
                            "Solana Program Library Token",
                            "StatemineAsset",
                            "StatemintAsset",
                            "TRON TRC-10 contract standard",
                            "TRON TRC-20 contract standard",
                            "SDX",
                            "Simple Ledger Protocol",
                            "Waves Smart Contracts"
                        ]
                    }
                },
                "AuxiliaryDistributedLedger": {
                    "condition": "Conditionally required for non provisional records",
                    "title": "Auxiliary Digital Token Distributed Ledger",
                    "description": "A DTI of a native digital token [DTIType=1] or of a distributed ledger without a distributed ledger [DTIType=2]. The distributed ledger of the DTI is used as the platform for the auxiliary digital token",
                    "type": "string"
                },
                "AuxiliaryTechnicalReference": {
                    "condition": "Conditionally required for non provisional records",
                    "title": "Auxiliary Digital Token Technical Reference",
                    "description": "Element, such as a smart contract address, used to uniquely identify an auxiliary digital token\u2019s origin on a distributed ledger technology platform",
                    "type": "string"
                }
            },
            "additionalProperties": false
        },
        "Metadata": {
            "type": "object",
            "properties": {
                "recVersion": {
                    "title": "Record Version",
                    "description": "The version of the record, incremental integer starting at 1 and incrementing each time the record is updated (e.g. with a new fork)",
                    "type": "integer"
                },
                "recDateTime": {
                    "title": "Record Date Time",
                    "description": "The time at which this record version has been created",
                    "type": "string",
                    "pattern": "^[0-9]{4}-[0-9]{2}-[0-9]{2}T[0-9]{2}:[0-9]{2}:[0-9]{2}(\\.[0-9]*)?$",
                    "format": "date-time"
                },
                "Provisional": {
                    "title": "Provisional Digital Token Identifier",
                    "description": "If true, the record contains normative or informative data elements in a provisional request for a DTI when one or more data elements (which may include mandatory data elements) are not yet available",
                    "type": "boolean",
                    "default": false
                },
                "Private": {
                    "title": "Private Digital Token",
                    "description": "If true, the record contains normative or informative data elements that are verified according to the DTIF guidelines but may not be independently verifiable by the general public",
                    "type": "boolean",
                    "default": false
                },
                "Disputed": {
                    "title": "Disputed Digital Token Identifier",
                    "description": "If true, the record contains normative or informative data elements that are disputed by one or more DTIF users",
                    "type": "boolean",
                    "default": false
                },
                "Deleted": {
                    "title": "Deleted Digital Token Identifier",
                    "description": "Record is marked Deleted due to technical reason(s) (e.g. invalid or duplicate token) or due to business reason(s) (e.g. a provisional token becomes invalid). Users are advised not to use this token.",
                    "type": "boolean",
                    "default": false
                }
            },
            "required": [
                "recVersion",
                "recDateTime"
            ],
            "additionalProperties": false
        }
    },
    "required": [
        "Header",
        "Informative",
        "Normative",
        "Metadata"
    ],
    "additionalProperties": false
}
